MANIFEST.in
README.rst
setup.py
wagtail_blog/__init__.py
wagtail_blog/admin.py
wagtail_blog/feeds.py
wagtail_blog/models.py
wagtail_blog/tests.py
wagtail_blog/views.py
wagtail_blog/wagtail_hooks.py
wagtail_blog/migrations/0001_initial.py
wagtail_blog/migrations/__init__.py
wagtail_blog/templates/wagtail_blog/blog_index_page.html
wagtail_blog/templates/wagtail_blog/blog_page.html
wagtail_blog/templates/wagtail_blog/fragments/paginator.html
wagtail_blog/templates/wagtail_blog/fragments/related.html
wagtail_blog/templates/wagtail_blog/fragments/tags.html
wagtail_blog_app.egg-info/PKG-INFO
wagtail_blog_app.egg-info/SOURCES.txt
wagtail_blog_app.egg-info/dependency_links.txt
wagtail_blog_app.egg-info/requires.txt
wagtail_blog_app.egg-info/top_level.txt