Metadata-Version: 1.1
Name: wagtail-blog-app
Version: 0.1.2
Summary: Simple wagtail blog for your Django project.
Home-page: http://www.tivix.com/
Author: Sumit Chachra
Author-email: chachra@tivix.com
License: UNKNOWN
Keywords: django wagtail blog app tivix
Platform: UNKNOWN
Classifier: Environment :: Web Environment
Classifier: Framework :: Django
Classifier: Intended Audience :: Developers
Classifier: Operating System :: OS Independent
Classifier: Topic :: Software Development
